rune/__init__.py
rune/bootstrap.py
rune/context.py
rune/cli/__init__.py
rune/cli/configcli.py
rune/cli/profilecli.py
rune/cli/secretcli.py
rune/cli/sessioncli.py
rune/cli/usercli.py
rune/commands/__init__.py
rune/commands/addcmd.py
rune/commands/deletecmd.py
rune/commands/getcmd.py
rune/commands/listcmd.py
rune/commands/logincmd.py
rune/commands/movecmd.py
rune/commands/updatecmd.py
rune/crypto/__init__.py
rune/crypto/aesgcm.py
rune/crypto/base.py
rune/crypto/factory.py
rune/exception/__init__.py
rune/exception/badinput.py
rune/exception/notfounderror.py
rune/exception/session.py
rune/exception/wrongencryption.py
rune/exception/wrongkey.py
rune/internal/__init__.py
rune/internal/add.py
rune/internal/delete.py
rune/internal/get.py
rune/internal/listsecrets.py
rune/internal/move.py
rune/internal/update.py
rune/models/__init__.py
rune/models/result.py
rune/models/crypto/__init__.py
rune/models/crypto/namespace.py
rune/models/crypto/secret.py
rune/models/crypto/secretfield.py
rune/models/session/__init__.py
rune/models/session/status.py
rune/models/session/protocol/__init__.py
rune/models/session/protocol/command.py
rune/models/session/protocol/response.py
rune/models/settings/__init__.py
rune/models/settings/encryptionsettings.py
rune/models/settings/sessionsettings.py
rune/models/settings/settings.py
rune/models/settings/storagesettings.py
rune/session/__init__.py
rune/session/base.py
rune/session/daemonmgr.py
rune/session/factory.py
rune/session/mock.py
rune/session/daemon/__init__.py
rune/session/daemon/__main__.py
rune/session/daemon/process.py
rune/storage/__init__.py
rune/storage/secrets/__init__.py
rune/storage/secrets/base.py
rune/storage/secrets/factory.py
rune/storage/secrets/local.py
rune/storage/settings/__init__.py
rune/storage/settings/settingsstorage.py
rune/utils/__init__.py
rune/utils/display.py
rune/utils/environment.py
rune/utils/formatting.py
rune/utils/input.py
rune-0.8.0.dist-info/licenses/LICENSE
rune-0.8.0.dist-info/METADATA
rune-0.8.0.dist-info/WHEEL
rune-0.8.0.dist-info/entry_points.txt
rune-0.8.0.dist-info/top_level.txt
rune-0.8.0.dist-info/RECORD
