Metadata-Version: 2.4
Name: rune
Version: 0.8.0
Summary: A local-first, client-side encrypted secrets manager for developers.
Author: sawsent
License: Copyright 2025 sawsent
Project-URL: Homepage, https://github.com/sawsent/rune
Project-URL: Repository, https://github.com/sawsent/rune
Project-URL: Issues, https://github.com/sawsent/rune/issues
Keywords: secrets,encryption,cli,vault,credentials,security,developer-tools,devops
Classifier: Development Status :: 4 - Beta
Classifier: Intended Audience :: Developers
Classifier: Environment :: Console
Classifier: Operating System :: OS Independent
Classifier: Programming Language :: Python :: 3
Classifier: Programming Language :: Python :: 3 :: Only
Classifier: License :: OSI Approved :: Apache Software License
Classifier: Topic :: Security :: Cryptography
Classifier: Topic :: Utilities
Requires-Python: >=3.8
License-File: LICENSE
Requires-Dist: typer>=0.12
Requires-Dist: pyperclip>=1.8
Requires-Dist: platformdirs>=4.0
Requires-Dist: cryptography>=41.0
Dynamic: license-file
